Metadata-Version: 1.2
Name: pytest-tape
Version: 0.1.0
Summary: easy assertion with expected results saved to yaml files
Home-page: https://github.com/a-chugunov/pytest-tape
Author: Alexey Chugunov
Author-email: alexey@chugunov.dev
Maintainer: Alexey Chugunov
Maintainer-email: alexey@chugunov.dev
License: MIT
Project-URL: Tracker, https://github.com/a-chugunov/pytest-tape/issues
Project-URL: Source, https://github.com/a-chugunov/pytest-tape
Project-URL: Documentation, https://a-chugunov.github.io/pytest-tape
Platform: UNKNOWN
Classifier: Development Status :: 4 - Beta
Classifier: Framework :: Pytest
Classifier: Intended Audience :: Developers
Classifier: Topic :: Software Development :: Testing
Classifier: Programming Language :: Python
Classifier: Programming Language :: Python :: 3
Classifier: Programming Language :: Python :: 3.6
Classifier: Programming Language :: Python :: 3.7
Classifier: Programming Language :: Python :: 3.8
Classifier: Programming Language :: Python :: 3.9
Classifier: Programming Language :: Python :: 3 :: Only
Classifier: Programming Language :: Python :: Implementation :: CPython
Classifier: Programming Language :: Python :: Implementation :: PyPy
Classifier: Operating System :: OS Independent
Classifier: License :: OSI Approved :: MIT License
Requires-Python: >=3.6
